Workbook

Sheet Financial Dashboard
A1: Startup
A2: Minor Financial Projections for a pitch deck
B4: Legend
B5: Provided by client
B6: Assumed | D6: Note: Can be changed
B7: Calculated | D7: Note: Should not be changed
M30: 9.1
M31: Total Increase in Revenue

Sheet Monthly BrakeDown
B1: Financials
B2: Income statement projection
A4: Revenue * | B4: Assumtion data | C4: 1st Month | D4: 2nd | E4: 3rd | F4: 4th | G4: 5th | H4: 6th | I4: Next Phase | J4: 7th | K4: 8th | L4: 9th | M4: 10th | N4: 11th | O4: 12th | P4: Year 1 | Q4: Year 2 | R4: Year 3
A5: Total number of New users | B5: =SUM('Customer Acquisition'!D38) -> 3952.2968 | C5: =SUM(B5*B7) -> 988.0742 | D5: =SUM(B5*C7) -> 1976.1484 | E5: =SUM(B5*D7) -> 2964.2226 | F5: =SUM(B5*E7) -> 3952.2968 | G5: =SUM(B5*F7) -> 10483.791 | H5: =SUM(B5*G7) -> 13437.753 | J5: =SUM(B5*H7) -> 14028.811 | K5: =SUM(B5*J7) -> 21297.582 | L5: =SUM(B5*K7) -> 31309.22 | M5: =SUM(B5*L7) -> 43748.909 | N5: =SUM(B5*M7) -> 56704.902 | O5: =SUM(B5*N7) -> 81727.756 | P5: =SUM(O11) -> 268488.49 | Q5: =SUM(P5*Q7) -> 536976.99 | R5: =SUM(Q5*R7) -> 1073954
A6: Total Active users | C6: =SUM(C12) -> 281.60115 | D6: =SUM(D12) -> 844.80344 | E6: =SUM(E12) -> 1689.6069 | F6: =SUM(F12) -> 2816.0115 | G6: =SUM(G12) -> 5803.892 | H6: =SUM(H12) -> 9633.6515 | J6: =SUM(J12) -> 13631.863 | K6: =SUM(K12) -> 19701.674 | L6: =SUM(L12) -> 28624.801 | M6: =SUM(M12) -> 41093.24 | N6: =SUM(N12) -> 57254.137 | O6: =SUM(O12) -> 80546.548 | P6: =SUM(P12) -> 80546.548 | Q6: =SUM(Q12) -> 241639.64 | R6: =SUM(R12) -> 563825.84
A7: Monthly Grow Rate | B7: 0.25 | C7: 0.5 | D7: 0.75 | E7: 1 | F7: =Max(0,E44) -> 2.652582 | G7: =Max(0,F44) -> 3.3999857 | H7: =Max(0,G44) -> 3.5495338 | J7: =Max(0,I44) -> 5.3886597 | K7: =Max(0,J44) -> 7.9217787 | L7: =Max(0,K44) -> 11.069237 | M7: =Max(0,L44) -> 14.347329 | N7: =Max(0,M44) -> 20.678547 | O7: =Max(0,N44) -> 25.578685 | Q7: 2 | R7: 2
A8: Churn Rate | C8: 0.05 | D8: 0.05 | E8: 0.05 | F8: 0.05 | G8: 0.05 | H8: 0.05 | J8: 0.05 | K8: 0.05 | L8: 0.05 | M8: 0.05 | N8: 0.05 | O8: 0.05
A9: Active Rate | C9: =SUM('Income Statement'!D4) -> 0.3 | D9: =SUM(C9) -> 0.3 | E9: =SUM(D9) -> 0.3 | F9: =SUM(E9) -> 0.3 | G9: =SUM(F9) -> 0.3 | H9: =SUM(G9) -> 0.3 | J9: =SUM(H9) -> 0.3 | K9: =SUM(J9) -> 0.3 | L9: =SUM(K9) -> 0.3 | M9: =SUM(L9) -> 0.3 | N9: =SUM(M9) -> 0.3 | O9: =SUM(N9) -> 0.3 | P9: =SUM(O9) -> 0.3 | Q9: =SUM(P9) -> 0.3 | R9: =SUM(Q9) -> 0.3
A10: Total Downloads | C10: =SUM(C5) -> 988.0742 | D10: =SUM(C10+D5) -> 2964.2226 | E10: =SUM(D10+E5) -> 5928.4452 | F10: =SUM(E10+F5) -> 9880.742 | G10: =SUM(F10+G5) -> 20364.533 | H10: =SUM(G10+H5) -> 33802.286 | J10: =SUM(H10+J5) -> 47831.097 | K10: =SUM(J10+K5) -> 69128.679 | L10: =SUM(K10+L5) -> 100437.9 | M10: =SUM(L10+M5) -> 144186.81 | N10: =SUM(M10+N5) -> 200891.71 | O10: =SUM(N10+O5) -> 282619.47
A11: Total User | C11: =SUM(C10-(C10*C8)) -> 938.67049 | D11: =SUM(D10-(D10*D8)) -> 2816.0115 | E11: =SUM(E10-(E10*E8)) -> 5632.0229 | F11: =SUM(F10-(F10*F8)) -> 9386.7049 | G11: =SUM(G10-(G10*G8)) -> 19346.307 | H11: =SUM(H10-(H10*H8)) -> 32112.172 | J11: =SUM(J10-(J10*J8)) -> 45439.542 | K11: =SUM(K10-(K10*K8)) -> 65672.245 | L11: =SUM(L10-(L10*L8)) -> 95416.005 | M11: =SUM(M10-(M10*M8)) -> 136977.47 | N11: =SUM(N10-(N10*N8)) -> 190847.12 | O11: =SUM(O10-(O10*O8)) -> 268488.49 | P11: =SUM(O11) -> 268488.49 | Q11: =SUM(P11+Q5) -> 805465.48 | R11: =SUM(Q11+R5) -> 1879419.5
A12: MAU | B12: 1 | C12: =SUM(C11*C9) -> 281.60115 | D12: =SUM(D11*D9) -> 844.80344 | E12: =SUM(E11*E9) -> 1689.6069 | F12: =SUM(F11*F9) -> 2816.0115 | G12: =SUM(G11*G9) -> 5803.892 | H12: =SUM(H11*H9) -> 9633.6515 | J12: =SUM(J11*J9) -> 13631.863 | K12: =SUM(K11*K9) -> 19701.674 | L12: =SUM(L11*L9) -> 28624.801 | M12: =SUM(M11*M9) -> 41093.24 | N12: =SUM(N11*N9) -> 57254.137 | O12: =SUM(O11*O9) -> 80546.548 | P12: =SUM(P11*P9) -> 80546.548 | Q12: =SUM(Q11*Q9) -> 241639.64 | R12: =SUM(R11*R9) -> 563825.84
A13: Number of new Business on app | B13: =SUM('Customer Acquisition'!D62) -> 158.33333 | C13: =SUM(B13*C14) -> 158.33333 | D13: =SUM(B13*D14) -> 158.33333 | E13: =SUM(B13*E14) -> 448.68399 | F13: =SUM(B13*F14) -> 406.22063 | G13: =SUM(B13*G14) -> 338.33226 | H13: =SUM(B13*H14) -> 349.54836 | I13: =SUM(B13*I14) -> 474.31683 | J13: =SUM(I13+(C13*3)) -> 949.31683 | K13: =SUM(D13*K14) -> 656.7014 | L13: =SUM(E13*L14) -> 2503.142 | M13: =SUM(F13*M14) -> 2871.7857 | N13: =SUM(G13*N14) -> 3365.9189 | O13: =SUM(H13*O14) -> 4256.3923 | P13: =SUM(C13:O13) -> 16937.026 | Q13: =P13+P13*Q14 -> 84685.13 | R13: =Q13+Q13*R14 -> 592795.91
A14: Annual Grow Rate | C14: 1 | D14: =Max(0,C49) -> 1 | E14: =Max(0,D49) -> 2.8337936 | F14: =Max(0,E49) -> 2.565604 | G14: =Max(0,F49) -> 2.1368353 | H14: =Max(0,G49) -> 2.2076739 | I14: =Max(0,H49) -> 2.9956853 | J14: =Max(0,H49) -> 2.9956853 | K14: =Max(0,J49) -> 4.1475878 | L14: =Max(0,K49) -> 5.5788529 | M14: =Max(0,L49) -> 7.0695222 | N14: =Max(0,M49) -> 9.9485604 | O14: =Max(0,N49) -> 12.176834 | P14: =AVERAGE(D14:O14) -> 4.6380529 | Q14: 4 | R14: =Q14*1.5 -> 6
A15: Churn rate | C15: 0.1 | D15: 0.1 | E15: 0.1 | F15: 0.1 | G15: 0.1 | H15: 0.1 | J15: 0.1 | K15: 0.1 | L15: 0.1 | M15: 0.1 | N15: 0.1 | O15: 0.1 | P15: 0.1 | Q15: 0.1 | R15: 0.1
A16: Paid Business Subscriber | C16: 0.1 | D16: 0.1 | E16: 0.2 | F16: 0.2 | G16: 0.2 | H16: 0.2 | J16: 0.3 | K16: 0.3 | L16: 0.3 | M16: 0.35 | N16: 0.35 | O16: 0.4
A17: No of City | C17: 1 | D17: 1 | E17: 1 | F17: 1 | G17: 1 | H17: 1 | J17: 4 | K17: 4 | L17: 4 | M17: 16 | N17: 16 | O17: 32 | P17: 64 | Q17: 120 | R17: 120
A18: Number of active new business users | C18: =C13-C13*C15 -> 142.5 | D18: =D13-D13*D15+C18 -> 285 | E18: =E13-E13*E15+D18 -> 688.81559 | F18: =F13-F13*F15+E18 -> 1054.4142 | G18: =G13-G13*G15+F18 -> 1358.9132 | H18: =H13-H13*H15+G18 -> 1673.5067 | J18: =J13-J13*J15+H18 -> 2527.8919 | K18: =K13-K13*K15+J18 -> 3118.9231 | L18: =L13-L13*L15+K18 -> 5371.7509 | M18: =M13-M13*M15+L18 -> 7956.3581 | N18: =N13-N13*N15+M18 -> 10985.685 | O18: =O13-O13*O15+N18 -> 14816.438 | P18: 39032.227 | Q18: =Q13-Q13*Q15+P18 -> 115248.84 | R18: =R13-R13*R15+Q18 -> 648765.16
A19: Commission on Sales | C19: =SUM(C6*Assumptions!C23*Assumptions!D23) -> 45760.186 | D19: =SUM(D6*Assumptions!C23*Assumptions!D23) -> 137280.56 | E19: =SUM(E6*Assumptions!C23*Assumptions!D23) -> 274561.12 | F19: =SUM(F6*Assumptions!C23*Assumptions!D23) -> 457601.86 | G19: =SUM(G6*Assumptions!C23*Assumptions!D23) -> 943132.45 | H19: =SUM(H6*Assumptions!C23*Assumptions!D23) -> 1565468.4 | J19: =SUM(J6*Assumptions!C23*Assumptions!D23) -> 2215177.7 | K19: =SUM(K6*Assumptions!C23*Assumptions!D23) -> 3201522 | L19: =SUM(L6*Assumptions!C23*Assumptions!D23) -> 4651530.2 | M19: =SUM(M6*Assumptions!C23*Assumptions!D23) -> 6677651.6 | N19: =SUM(N6*Assumptions!C23*Assumptions!D23) -> 9303797.3 | O19: =SUM(O6*Assumptions!C23*Assumptions!D23) -> 13088814 | P19: =SUM(C18:O19) -> 42612278 | Q19: =SUM(12*Q6*Assumptions!C23*Assumptions!D23) -> 4.7119731e+08 | R19: =SUM(12*R6*Assumptions!C23*Assumptions!D23) -> 1099460379
A20: Promoted Sales (5%) | C20: =SUM(C6*Assumptions!C24*Assumptions!D24) -> 18304.075 | D20: =SUM(D6*Assumptions!C24*Assumptions!D24) -> 54912.224 | E20: =SUM(E6*Assumptions!C24*Assumptions!D24) -> 109824.45 | F20: =SUM(F6*Assumptions!C24*Assumptions!D24) -> 183040.75 | G20: =SUM(G6*Assumptions!C24*Assumptions!D24) -> 377252.98 | H20: =SUM(H6*Assumptions!C24*Assumptions!D24) -> 626187.35 | J20: =SUM(J6*Assumptions!C24*Assumptions!D24) -> 886071.07 | K20: =SUM(K6*Assumptions!C24*Assumptions!D24) -> 1280608.8 | L20: =SUM(L6*Assumptions!C24*Assumptions!D24) -> 1860612.1 | M20: =SUM(M6*Assumptions!C24*Assumptions!D24) -> 2671060.6 | N20: =SUM(N6*Assumptions!C24*Assumptions!D24) -> 3721518.9 | O20: =SUM(O6*Assumptions!C24*Assumptions!D24) -> 5235525.6 | P20: =SUM(C20:O20) -> 17024919 | Q20: =SUM(12*Q6*Assumptions!C24*Assumptions!D24) -> 1.8847892e+08 | R20: =SUM(12*R6*Assumptions!C24*Assumptions!D24) -> 4.3978415e+08
A21: Business Subscription | B21: =SUM(Assumptions!E25) -> 1500 | C21: =SUM(B21*(C18*C16)) -> 21375 | D21: =SUM(B21*(D18*D16)) -> 42750 | E21: =SUM(B21*(E18*E16)) -> 206644.68 | F21: =SUM(B21*(F18*F16)) -> 316324.25 | G21: =SUM(B21*(G18*G16)) -> 407673.96 | H21: =SUM(B21*(H18*H16)) -> 502052.02 | J21: =SUM(B21*(J18*J16)) -> 1137551.3 | K21: =SUM(B21*(K18*K16)) -> 1403515.4 | L21: =SUM(B21*(L18*L16)) -> 2417287.9 | M21: =SUM(B21*(M18*M16)) -> 4177088 | N21: =SUM(B21*(N18*N16)) -> 5767484.7 | O21: =SUM(B21*(O18*O16)) -> 8889862.9 | P21: =SUM(C21:O21) -> 25289610 | Q21: =SUM(12*Q18*500) -> 6.9149306e+08 | R21: =SUM(12*R18*500) -> 3892590961
A22: Cash Store Afilates Commission | C22: =SUM(C6*Assumptions!C26*Assumptions!D26) -> 2816.0115 | D22: =SUM(D6*Assumptions!C26*Assumptions!D26) -> 8448.0344 | E22: =SUM(E6*Assumptions!C26*Assumptions!D26) -> 16896.069 | F22: =SUM(F6*Assumptions!C26*Assumptions!D26) -> 28160.115 | G22: =SUM(G6*Assumptions!C26*Assumptions!D26) -> 58038.92 | H22: =SUM(H6*Assumptions!C26*Assumptions!D26) -> 96336.515 | J22: =SUM(J6*Assumptions!C26*Assumptions!D26) -> 136318.63 | K22: =SUM(K6*Assumptions!C26*Assumptions!D26) -> 197016.74 | L22: =SUM(L6*Assumptions!C26*Assumptions!D26) -> 286248.01 | M22: =SUM(M6*Assumptions!C26*Assumptions!D26) -> 410932.4 | N22: =SUM(N6*Assumptions!C26*Assumptions!D26) -> 572541.37 | O22: =SUM(O6*Assumptions!C26*Assumptions!D26) -> 805465.48 | P22: =SUM(C22:O22) -> 2619218.3 | Q22: =SUM(12*Q6*Assumptions!C26*Assumptions!D26) -> 28996757 | R22: =SUM(12*R6*Assumptions!C26*Assumptions!D26) -> 67659100
A23: Subscription | C23: =SUM(C6*49) -> 13798.456 | D23: =SUM(D6*49) -> 41395.369 | E23: =SUM(E6*49) -> 82790.737 | F23: =SUM(F6*49) -> 137984.56 | G23: =SUM(G6*49) -> 284390.71 | H23: =SUM(H6*49) -> 472048.92 | J23: =SUM(J6*49) -> 667961.27 | K23: =SUM(K6*49) -> 965382.01 | L23: =SUM(L6*49) -> 1402615.3 | M23: =SUM(M6*49) -> 2013568.8 | N23: =SUM(N6*49) -> 2805452.7 | O23: =SUM(O6*49) -> 3946780.8 | P23: =SUM(C23:O23) -> 12834170 | Q23: =SUM(12*Q12*49) -> 1.4208411e+08 | R23: =SUM(12*R12*49) -> 3.3152959e+08
A24: Total Revenue | B24: 1 | C24: =SUM(C19:C23) -> 102053.73 | D24: =SUM(D19:D23) -> 284786.19 | E24: =SUM(E19:E23) -> 690717.05 | F24: =SUM(F19:F23) -> 1123111.5 | G24: =SUM(G19:G23) -> 2070489 | H24: =SUM(H19:H23) -> 3262093.2 | J24: =SUM(J19:J23) -> 5043080 | K24: =SUM(K19:K23) -> 7048044.9 | L24: =SUM(L19:L23) -> 10618294 | M24: =SUM(M19:M23) -> 15950301 | N24: =SUM(N19:N23) -> 22170795 | O24: =SUM(O19:O23) -> 31966449 | P24: =SUM(C24:O24) -> 1.0033021e+08 | Q24: =SUM(Q19:Q23) -> 1522250155 | R24: =SUM(R19:R23) -> 5831024183
A26: Expenses | I26: Next Phase Estimate
A27: Rent and office Expenses | B27: =SUM(C27) -> 66666.667 | C27: =median(50000,Assumptions!B10,200000) -> 66666.667 | D27: =SUM(C27) -> 66666.667 | E27: =SUM(D27) -> 66666.667 | F27: =SUM(E27) -> 66666.667 | G27: =SUM(F27) -> 66666.667 | H27: =SUM(G27) -> 66666.667 | I27: =SUM(H27+(C27*3)) -> 266666.67 | J27: =median(200000,Assumptions!F10+I27,800000) -> 280000 | K27: =SUM(J27) -> 280000 | L27: =SUM(K27) -> 280000 | M27: =SUM(L27*4) -> 1120000 | N27: =SUM(M27*4) -> 4480000 | O27: =SUM(N27*4) -> 17920000 | P27: =SUM(B27:O27) -> 25093333 | Q27: =SUM(12*P27*2) -> 602240000 | R27: =SUM(Q27) -> 602240000
A28: Team Building & Legal | B28: =SUM(C28) -> 66666.667 | C28: =MEDIAN(50000,Assumptions!B11, 300000) -> 66666.667 | D28: =SUM(C28) -> 66666.667 | E28: =SUM(D28) -> 66666.667 | F28: =SUM(E28*1.5) -> 100000 | G28: =SUM(F28) -> 100000 | H28: =SUM(G28) -> 100000 | I28: =SUM(H28+(C28*3)) -> 300000 | J28: =MEDIAN(150000,Assumptions!F11+I28, 900000) -> 313333.33 | K28: =SUM(J28) -> 313333.33 | L28: =SUM(K28*1.5) -> 470000 | M28: =SUM(L28*1.5) -> 705000 | N28: =SUM(M28*1.5) -> 1057500 | O28: =SUM(N28) -> 1057500 | P28: =SUM(B28:O28) -> 4783333.3 | Q28: =SUM(12*P28*2) -> 114800000 | R28: =SUM(Q28*2) -> 229600000
A29: Customer Support Costs | B29: =SUM(C29) -> 66666.667 | C29: =MIN(500000,Assumptions!B12) -> 66666.667 | D29: =SUM(C29) -> 66666.667 | E29: =SUM(D29) -> 66666.667 | F29: =SUM(E29*1.5) -> 100000 | G29: =SUM(F29) -> 100000 | H29: =SUM(G29) -> 100000 | I29: =SUM(H29+(C29*3)) -> 300000 | J29: =MEDIAN(150000,Assumptions!F12+I29, 900000) -> 313333.33 | K29: =SUM(J29) -> 313333.33 | L29: =SUM(K29*1.5) -> 470000 | M29: =SUM(L29*1.5) -> 705000 | N29: =SUM(M29*1.5) -> 1057500 | O29: =SUM(N29) -> 1057500 | P29: =SUM(B29:O29) -> 4783333.3 | Q29: =SUM(12*P29*2) -> 114800000 | R29: =SUM(Q29*2) -> 229600000
A30: Technology & Infrastructure Costs | B30: =SUM(C30) -> 166666.67 | C30: =SUM(Assumptions!B13) -> 166666.67 | D30: =SUM(C30) -> 166666.67 | E30: =SUM(D30) -> 166666.67 | F30: =SUM(E30*2) -> 333333.33 | G30: =SUM(F30) -> 333333.33 | H30: =SUM(G30) -> 333333.33 | I30: =SUM(H30) -> 333333.33 | J30: =MEDIAN(150000,Assumptions!H13, 1500000) -> 366666.67 | K30: =SUM(J30) -> 366666.67 | L30: =SUM(K30*1.5) -> 550000 | M30: =SUM(L30*1.5) -> 825000 | N30: =SUM(M30*1.5) -> 1237500 | O30: =SUM(N30) -> 1237500 | P30: =SUM(B30:O30) -> 6583333.3 | Q30: =SUM(12*P30*2) -> 158000000 | R30: =SUM(Q30*2) -> 316000000
A31: Business Development & Partnerships | B31: =SUM('Customer Acquisition'!C60) -> 1000 | C31: =SUM(B31*C13) -> 158333.33 | D31: =SUM(B31*D13) -> 158333.33 | E31: =SUM(B31*E13) -> 448683.99 | F31: =SUM(B31*F13) -> 406220.63 | G31: =SUM(B31*G13) -> 338332.26 | H31: =SUM(B31*H13) -> 349548.36 | I31: =SUM(B31*I13) -> 474316.83 | J31: =SUM(Assumptions!H14) -> 505983.5 | K31: =SUM(B31*K13) -> 656701.4 | L31: =SUM(B31*L13) -> 2503142 | M31: =SUM(B31*M13) -> 2871785.7 | N31: =SUM(B31*N13) -> 3365918.9 | O31: =SUM(B31*O13) -> 4256392.3 | P31: =SUM(B31:O31) -> 16494693 | Q31: =SUM(12*P31*2) -> 3.9587262e+08 | R31: =SUM(Q31*2) -> 7.9174524e+08
A32: Marketing & User Acquisition: | B32: =SUM(B43) -> 300000 | C32: =SUM(C43) -> 300000 | D32: =SUM(D43) -> 300000 | E32: =SUM(E43) -> 300000 | F32: =SUM(E43+E39) -> 795774.59 | G32: =SUM(F43+F39) -> 1019995.7 | H32: =SUM(G43+G39) -> 1064860.1 | I32: =SUM(H43+H39) -> 1879917.5 | J32: =SUM(Assumptions!H15) -> 1939917.5 | K32: =SUM(J43+J39) -> 2851840.3 | L32: =SUM(K43+K39) -> 3984925.2 | M32: =SUM(L43+L39) -> 5165038.4 | N32: =SUM(M43+M39) -> 7444277 | O32: =SUM(N43+N39) -> 9208326.6 | P32: =SUM(B32:O32) -> 36554873 | Q32: =SUM(12*P32*2) -> 8.7731695e+08 | R32: =SUM(Q32*2) -> 1754633901
A34: Total Expenses | B34: =SUM(B27:B32) -> 667666.67 | C34: =SUM(C27:C32) -> 825000 | D34: =SUM(D27:D32) -> 825000 | E34: =SUM(E27:E32) -> 1115350.7 | F34: =SUM(F27:F32) -> 1801995.2 | G34: =SUM(G27:G32) -> 1958328 | H34: =SUM(H27:H32) -> 2014408.5 | J34: =SUM(J27:J32) -> 3719234.3 | K34: =SUM(K27:K32) -> 4781875 | L34: =SUM(L27:L32) -> 8258067.2 | M34: =SUM(M27:M32) -> 11391824 | N34: =SUM(N27:N32) -> 18642696 | O34: =SUM(O27:O32) -> 34737219 | P34: =SUM(P27:P32) -> 94292899 | Q34: =SUM(Q30) -> 158000000 | R34: =SUM(R30) -> 316000000
A35: Net | B35: =SUM(B24-B34) -> -667665.67 | C35: =SUM(C24-C34) -> -722946.27 | D35: =SUM(D24-D34) -> -540213.81 | E35: =SUM(E24-E34) -> -424633.61 | F35: =SUM(F24-F34) -> -678883.69 | G35: =SUM(G24-G34) -> 112161.04 | H35: =SUM(H24-H34) -> 1247684.7 | J35: =SUM(J24-J34) -> 1323845.6 | K35: =SUM(K24-K34) -> 2266169.8 | L35: =SUM(L24-L34) -> 2360226.3 | M35: =SUM(M24-M34) -> 4558477.3 | N35: =SUM(N24-N34) -> 3528099.1 | O35: =SUM(O24-O34) -> -2770769.9 | P35: =SUM(P24-P34) -> 6037315.5 | Q35: =SUM(Q24-Q34) -> 1364250155 | R35: =SUM(R24-R34) -> 5515024183
A37: Cash In hand (if budget is fixed) | B37: =SUM((B24+Assumptions!B8)-B34) -> 4332334.3 | C37: =SUM((C24+Assumptions!B8)-C34) -> 4277053.7 | D37: =SUM(((D24+Assumptions!C8)-D34)+C37) -> 3736839.9 | E37: =SUM(((E24+Assumptions!H26)-E34)+D37) -> 3312206.3 | F37: =SUM(((F24+Assumptions!I26)-F34)+E37) -> 2633322.6 | G37: =SUM(((G24+Assumptions!J26)-G34)+F37) -> 2745483.6 | H37: =SUM(((H24+Assumptions!G8)-H34)+G37) -> 3993168.3 | I37: =SUM(H37+Assumptions!F6) -> 4493168.3 | J37: =SUM(((J24+Assumptions!H8)-J34)+I37) -> 5817014 | K37: =SUM(((K24+Assumptions!K8)-K34)+J37) -> 8083183.8 | L37: =SUM(((L24+Assumptions!L8)-L34)+K37) -> 10443410 | M37: =SUM(((M24+Assumptions!M8)-M34)+L37) -> 15001887 | N37: =SUM(((N24+Assumptions!N8)-N34)+M37) -> 18529986 | O37: =SUM(((O24+Assumptions!O8)-O34)+N37) -> 15759217 | P37: =SUM(((P24+Assumptions!P8)-P34)+O37) -> 21796532 | Q37: =SUM(((Q24+Assumptions!Q8)-Q34)+P37) -> 1386046687 | R37: =SUM(((R24+Assumptions!R8)-R34)+Q37) -> 6901070870
A38: Surplus cash (can be used for next month) | D38: =SUM(D37-Assumptions!B9) -> 2903506.6 | E38: =SUM(E37-Assumptions!B9) -> 2478873 | F38: =SUM(F37-Assumptions!B9) -> 1799989.3 | G38: =SUM(G37-Assumptions!B9) -> 1912150.3 | H38: =SUM(H37-Assumptions!B9) -> 3159835 | I38: =SUM(H38) -> 3159835 | J38: =SUM(J37-Assumptions!B9) -> 4983680.6 | K38: =SUM(K37-Assumptions!B9) -> 7249850.5 | L38: =SUM(L37-Assumptions!B9) -> 9610076.8 | M38: =SUM(M37-Assumptions!B9) -> 14168554 | N38: =SUM(N37-Assumptions!B9) -> 17696653 | O38: =SUM(O37-Assumptions!B9) -> 14925883 | P38: =SUM(P37-50000000) -> -28203468 | Q38: =SUM(Q37-50000000) -> 1336046687 | R38: =SUM(R37-50000000) -> 6851070870
A39: Additional budget for Markeitng (next month) | E39: =MAX(0,E43*E45) -> 495774.59 | F39: =MAX(0,F43*F45) -> 719995.71 | G39: =MAX(0,G43*G45) -> 764860.13 | H39: =MAX(0,H43*H45) -> 1579917.5 | I39: =MAX(0,I43*I45) -> 1579917.5 | J39: =MAX(0,J43*J45) -> 2491840.3 | K39: =MAX(0,K43*K45) -> 3624925.2 | L39: =MAX(0,L43*L45) -> 4805038.4 | ... O39: =MAX(0,O43*O45) -> 7462941.6 | P39: =SUM(P43*P45) -> -19742428 | Q39: =SUM(Q43*Q45) -> 9.3523268e+08 | R39: =SUM(R43*R45) -> 4795749609
A40: Additional budget for BD (next month) | D40: =MAX(0,D48*D50) -> 290350.66 | E40: =MAX(0,E48*E50) -> 247887.3 | F40: =MAX(0,F48*F50) -> 179998.93 | G40: =MAX(0,G48*G50) -> 191215.03 | H40: =MAX(0,H48*H50) -> 315983.5 | I40: =MAX(0,I48*I50) -> 315983.5 | J40: =MAX(0,J48*J50) -> 498368.06 | K40: =MAX(0,K48*K50) -> 724985.05 | ... O40: =MAX(0,O48*O50) -> 1492588.3
A41: Final Cash Left (after additional use) | B41: =SUM(B37-(B38*B46)) -> 4332334.3 | C41: =SUM(C37-(C38*C46)) -> 4277053.7 | D41: =SUM(D37-(D38*D46)) -> 3736839.9 | E41: =SUM((D41+E24)-E34) -> 3312206.3 | F41: =SUM((E41+F24)-F34) -> 2633322.6 | G41: =SUM((F41+G24)-G34) -> 2745483.6 | H41: =SUM((G41+H24)-H34) -> 3993168.3 | I41: =SUM(H41+Assumptions!F6) -> 4493168.3 | J41: =SUM((I41+J24)-J34) -> 5817014 | K41: =SUM((J41+K24)-K34) -> 8083183.8 | L41: =SUM((K41+L24)-L34) -> 10443410 | M41: =SUM((L41+M24)-M34) -> 15001887 | N41: =SUM((M41+N24)-N34) -> 18529986 | O41: =SUM((N41+O24)-O34) -> 15759217
A43: Marketing budget Fixed | B43: =SUM('Customer Acquisition'!B38) -> 300000 | C43: =SUM(B43) -> 300000 | D43: =SUM(C43) -> 300000 | E43: =SUM(D43) -> 300000 | F43: =SUM(E43) -> 300000 | G43: =SUM(F43) -> 300000 | H43: =SUM(G43) -> 300000 | I43: =SUM(H43+Assumptions!F15) -> 360000 | J43: =SUM(I43) -> 360000 | K43: =SUM(J43) -> 360000 | L43: =SUM(K43) -> 360000 | M43: =SUM(L43) -> 360000 | N43: =SUM(M43) -> 360000 | O43: =SUM(N43) -> 360000 | P43: =SUM(O43) -> 360000 | Q43: =SUM(P43) -> 360000 | R43: =SUM(Q43) -> 360000
B44: =SUM(1+(B45)) -> 1 | C44: =SUM(1+(C45)) -> 1 | D44: =SUM(1+(D45)) -> 8.7426842 | E44: =SUM(1+(E45)) -> 2.652582 | F44: =SUM(1+(F45)) -> 3.3999857 | G44: =SUM(1+(G45)) -> 3.5495338 | H44: =SUM(1+(H45)) -> 6.2663916 | I44: =SUM(1+(I45)) -> 5.3886597 | ... O44: =SUM(1+(O45)) -> 21.730393
A45: Additional budget for Markeitng ( multiple) | B45: =SUM((B38*0.8)/B43) -> 0 | C45: =SUM((C38*0.8)/C43) -> 0 | D45: =SUM((D38*0.8)/D43) -> 7.7426842 | E45: =max(0,(E38*E46)/E43) -> 1.652582 | F45: =max(0,(F38*F46)/F43) -> 2.3999857 | G45: =max(0,(G38*G46)/G43) -> 2.5495338 | H45: =max(0,(H38*H46)/H43) -> 5.2663916 | I45: =max(0,(I38*I46)/I43) -> 4.3886597 | J45: =max(0,(J38*J46)/J43) -> 6.9217787 | K45: =max(0,(K38*K46)/K43) -> 10.069237 | L45: =max(0,(L38*L46)/L43) -> 13.347329 | ... O45: =max(0,(O38*O46)/O43) -> 20.730393 | P45: =SUM((P38*0.7)/P43) -> -54.840077 | Q45: =SUM((Q38*0.7)/Q43) -> 2597.8686 | R45: =SUM((R38*0.7)/R43) -> 13321.527
A46: Percentage used in marketing (surplus) | E46: 0.2 | F46: 0.4 | G46: 0.4 | H46: 0.5 | I46: 0.5 | J46: 0.5 | K46: 0.5 | L46: 0.5 | M46: 0.5 | N46: 0.5 | O46: 0.5
A48: Business Development Fixed Cost | B48: =SUM(Assumptions!B14) -> 158333.33 | C48: =SUM(B48) -> 158333.33 | D48: =SUM(C48) -> 158333.33 | E48: =SUM(D48) -> 158333.33 | F48: =SUM(E48) -> 158333.33 | G48: =SUM(F48) -> 158333.33 | H48: =SUM(G48) -> 158333.33 | I48: =SUM(H48) -> 158333.33 | J48: =SUM(I48) -> 158333.33 | ... O48: =SUM(N48) -> 158333.33
B49: =SUM(1+B50) -> 1 | C49: =SUM(1+C50) -> 1 | D49: =SUM(1+D50) -> 2.8337936 | E49: =SUM(1+E50) -> 2.565604 | F49: =SUM(1+F50) -> 2.1368353 | G49: =SUM(1+G50) -> 2.2076739 | H49: =SUM(1+H50) -> 2.9956853 | I49: =SUM(1+I50) -> 2.9956853 | ... O49: =SUM(1+O50) -> 10.426874
A50: Additional budget for bd ( multiple) | D50: =max(0,(D38*D51)/D48) -> 1.8337936 | E50: =max(0,(E38*E51)/E48) -> 1.565604 | F50: =max(0,(F38*F51)/F48) -> 1.1368353 | G50: =max(0,(G38*G51)/G48) -> 1.2076739 | H50: =max(0,(H38*H51)/H48) -> 1.9956853 | I50: =max(0,(I38*I51)/I48) -> 1.9956853 | J50: =max(0,(J38*J51)/J48) -> 3.1475878 | K50: =max(0,(K38*K51)/K48) -> 4.5788529 | ... O50: =max(0,(O38*O51)/O48) -> 9.4268736
A51: Percentage used in BD (surplus) | D51: 0.1 | E51: 0.1 | F51: 0.1 | G51: 0.1 | H51: 0.1 | I51: 0.1 | J51: 0.1 | K51: 0.1 | L51: 0.1 | M51: 0.1 | N51: 0.1 | O51: 0.1
A54: Fixed Cost | C54: =SUM(C30,C28,C27,C29) -> 366666.67 | D54: =SUM(D30,D28,D27,D29) -> 366666.67 | E54: =SUM(E30,E28,E27,E29) -> 366666.67 | F54: =SUM(F30,F28,F27,F29) -> 600000 | G54: =SUM(G30,G28,G27,G29) -> 600000 | H54: =SUM(H30,H28,H27,H29) -> 600000 | J54: =SUM(J30,J28,J27,J29) -> 1273333.3 | K54: =SUM(K30,K28,K27,K29) -> 1273333.3 | L54: =SUM(L30,L28,L27,L29) -> 1770000 | M54: =SUM(M30,M28,M27,M29) -> 3355000 | N54: =SUM(N30,N28,N27,N29) -> 7832500 | O54: =SUM(O30,O28,O27,O29) -> 21272500 | P54: =SUM(P30,P28,P27,P29) -> 41243333 | Q54: =SUM(Q30,Q28,Q27,Q29) -> 989840000 | R54: =SUM(R30,R28,R27,R29) -> 1377440000
A55: Variable Cost | B55: =SUM(B32,B31) -> 301000 | C55: =SUM(C32,C31) -> 458333.33 | D55: =SUM(D32,D31) -> 458333.33 | E55: =SUM(E32,E31) -> 748683.99 | F55: =SUM(F32,F31) -> 1201995.2 | G55: =SUM(G32,G31) -> 1358328 | H55: =SUM(H32,H31) -> 1414408.5 | J55: =SUM(J32,J31) -> 2445901 | K55: =SUM(K32,K31) -> 3508541.7 | L55: =SUM(L32,L31) -> 6488067.2 | M55: =SUM(M32,M31) -> 8036824.1 | N55: =SUM(N32,N31) -> 10810196 | O55: =SUM(O32,O31) -> 13464719 | P55: =SUM(P32,P31) -> 53049566 | Q55: =SUM(Q32,Q31) -> 1273189573 | R55: =SUM(R32,R31) -> 2546379146
A56: Gross Margin (%) | C56: =SUM((C24-C34)/C24) -> -7.0839771 | D56: =SUM((D24-D34)/D24) -> -1.8969102 | E56: =SUM((E24-E34)/E24) -> -0.61477216 | F56: =SUM((F24-F34)/F24) -> -0.60446685 | G56: =SUM((G24-G34)/G24) -> 0.054171278 | H56: =SUM((H24-H34)/H24) -> 0.38247978 | J56: =SUM((J24-J34)/J24) -> 0.26250737 | K56: =SUM((K24-K34)/K24) -> 0.3215317 | L56: =SUM((L24-L34)/L24) -> 0.22227925 | M56: =SUM((M24-M34)/M24) -> 0.28579255 | N56: =SUM((N24-N34)/N24) -> 0.15913273 | O56: =SUM((O24-O34)/O24) -> -0.08667744 | P56: =SUM((P24-P34)/P24) -> 0.060174451 | Q56: =SUM((Q24-Q34)/Q24) -> 0.89620628 | R56: =SUM((R24-R34)/R24) -> 0.94580712
A57: Gross Margin | C57: =SUM((C24-C34)) -> -722946.27 | D57: =SUM((D24-D34)) -> -540213.81 | E57: =SUM((E24-E34)) -> -424633.61 | F57: =SUM((F24-F34)) -> -678883.69 | G57: =SUM((G24-G34)) -> 112161.04 | H57: =SUM((H24-H34)) -> 1247684.7 | J57: =SUM((J24-J34)) -> 1323845.6 | K57: =SUM((K24-K34)) -> 2266169.8 | L57: =SUM((L24-L34)) -> 2360226.3 | M57: =SUM((M24-M34)) -> 4558477.3 | N57: =SUM((N24-N34)) -> 3528099.1 | O57: =SUM((O24-O34)) -> -2770769.9 | P57: =SUM((P24-P34)) -> 6037315.5 | Q57: =SUM((Q24-Q34)) -> 1364250155 | R57: =SUM((R24-R34)) -> 5515024183
A58: Net Profit Margin | C58: =SUM(C24-C34) -> -722946.27 | D58: =SUM(D24-D34) -> -540213.81 | E58: =SUM(E24-E34) -> -424633.61 | F58: =SUM(F24-F34) -> -678883.69 | G58: =SUM(G24-G34) -> 112161.04 | H58: =SUM(H24-H34) -> 1247684.7 | J58: =SUM(J24-J34) -> 1323845.6 | K58: =SUM(K24-K34) -> 2266169.8 | L58: =SUM(L24-L34) -> 2360226.3 | M58: =SUM(M24-M34) -> 4558477.3 | N58: =SUM(N24-N34) -> 3528099.1 | O58: =SUM(O24-O34) -> -2770769.9 | P58: =SUM(P24-P34) -> 6037315.5 | Q58: =SUM(Q24-Q34) -> 1364250155 | R58: =SUM(R24-R34) -> 5515024183
A59: Contribution Margin | C59: =SUM((C24-(C32+C31))) -> -356279.6 | D59: =SUM((D24-(D32+D31))) -> -173547.15 | E59: =SUM((E24-(E32+E31))) -> -57966.943 | F59: =SUM((F24-(F32+F31))) -> -78883.692 | G59: =SUM((G24-(G32+G31))) -> 712161.04 | H59: =SUM((H24-(H32+H31))) -> 1847684.7 | J59: =SUM((J24-(J32+J31))) -> 2597179 | K59: =SUM((K24-(K32+K31))) -> 3539503.2 | L59: =SUM((L24-(L32+L31))) -> 4130226.3 | M59: =SUM((M24-(M32+M31))) -> 7913477.3 | N59: =SUM((N24-(N32+N31))) -> 11360599 | O59: =SUM((O24-(O32+O31))) -> 18501730 | P59: =SUM((P24-(P32+P31))) -> 47280649 | Q59: =SUM((Q24-(Q32+Q31))) -> 2.4906058e+08 | R59: =SUM((R24-(R32+R31))) -> 3284645038
A60: CM per User | C60: =SUM(C59/C12) -> -1265.1923 | D60: =SUM(D59/D12) -> -205.42903 | E60: =SUM(E59/E12) -> -34.307947 | F60: =SUM(F59/F12) -> -28.012561 | G60: =SUM(G59/G12) -> 122.70405 | H60: =SUM(H59/H12) -> 191.79484 | J60: =SUM(J59/J12) -> 190.52268 | K60: =SUM(K59/K12) -> 179.65495 | L60: =SUM(L59/L12) -> 144.28838 | M60: =SUM(M59/M12) -> 192.5737 | N60: =SUM(N59/N12) -> 198.42407 | O60: =SUM(O59/O12) -> 229.70233 | P60: =SUM(P59/P12) -> 586.99783 | Q60: =SUM(Q59/Q12) -> 1030.7108 | R60: =SUM(R59/R12) -> 5825.6377
A61: Break Even Point | C61: =SUM((C54*(C59/C24))) -> -1280069.4 | D61: =SUM((D54*(D59/D24))) -> -223444.67 | E61: =SUM((E54*(E59/E24))) -> -30771.711 | F61: =SUM((F54*(F59/F24))) -> -42142.043 | G61: =SUM((G54*(G59/G24))) -> 206374.74 | H61: =SUM((H54*(H59/H24))) -> 339846.46 | J61: =SUM((J54*(J59/J24))) -> 655764.85 | K61: =SUM((K54*(K59/K24))) -> 639463.49 | L61: =SUM((L54*(L59/L24))) -> 688481.68 | M61: =SUM((M54*(M59/M24))) -> 1664527.6 | N61: =SUM((N54*(N59/N24))) -> 4013473.2 | O61: =SUM((O54*(O59/O24))) -> 12312223 | P61: =SUM((P54*(P59/P24))) -> 19435935 | Q61: =SUM((Q54*(Q59/Q24))) -> 1.6195113e+08 | R61: =SUM((R54*(R59/R24))) -> 7.7591883e+08
A62: CMGR
A63: ARR | C63: =SUM(C24*12) -> 1224644.7 | D63: =SUM(D24*12) -> 3417434.2 | E63: =SUM(E24*12) -> 8288604.6 | F63: =SUM(F24*12) -> 13477338 | G63: =SUM(G24*12) -> 24845868 | H63: =SUM(H24*12) -> 39145118 | J63: =SUM(J24*12) -> 60516960 | K63: =SUM(K24*12) -> 84576539 | L63: =SUM(L24*12) -> 1.2741952e+08 | M63: =SUM(M24*12) -> 1.9140362e+08 | N63: =SUM(N24*12) -> 266049541 | O63: =SUM(O24*12) -> 3.8359739e+08 | P63: =SUM(P24*12) -> 1203962573 | Q63: =SUM(Q24*12) -> 18267001857 | R63: =SUM(R24*12) -> 69972290201
A64: MRR / ARR | D64: =SUM(D24/D63) -> 0.083333333 | E64: =SUM(E24/E63) -> 0.083333333 | F64: =SUM(F24/F63) -> 0.083333333 | G64: =SUM(G24/G63) -> 0.083333333 | H64: =SUM(H24/H63) -> 0.083333333 | J64: =SUM(J24/J63) -> 0.083333333 | K64: =SUM(K24/K63) -> 0.083333333 | L64: =SUM(L24/L63) -> 0.083333333 | M64: =SUM(M24/M63) -> 0.083333333 | N64: =SUM(N24/N63) -> 0.083333333 | O64: =SUM(O24/O63) -> 0.083333333
A65: GMV (Est.) | C65: =SUM(Assumptions!F23*C12) -> 915203.73 | D65: =SUM(Assumptions!F23*D12) -> 2745611.2 | E65: =SUM(Assumptions!F23*E12) -> 5491222.4 | F65: =SUM(Assumptions!F23*F12) -> 9152037.3 | G65: =SUM(Assumptions!F23*G12) -> 18862649 | H65: =SUM(Assumptions!F23*H12) -> 31309367 | J65: =SUM(Assumptions!F23*J12) -> 44303553 | K65: =SUM(Assumptions!F23*K12) -> 64030439 | L65: =SUM(Assumptions!F23*L12) -> 93030605 | M65: =SUM(Assumptions!F23*M12) -> 1.3355303e+08 | N65: =SUM(Assumptions!F23*N12) -> 1.8607595e+08 | O65: =SUM(Assumptions!F23*O12) -> 2.6177628e+08 | P65: =SUM(Assumptions!F23*P12) -> 2.6177628e+08 | Q65: =SUM(Assumptions!F23*Q12) -> 7.8532884e+08 | R65: =SUM(Assumptions!F23*R12) -> 1832433965
A66: Rule of 40
A67: TAM
A68: SAM
A69: SOM
A70: CAC | C70: =SUM(C32/C5) -> 303.62092 | D70: =SUM(D32/D5) -> 151.81046 | E70: =SUM(E32/E5) -> 101.20697 | F70: =SUM(F32/F5) -> 201.34485 | G70: =SUM(G32/G5) -> 97.292638 | H70: =SUM(H32/H5) -> 79.243915 | J70: =SUM(J32/J5) -> 138.28096 | K70: =SUM(K32/K5) -> 133.90441 | L70: =SUM(L32/L5) -> 127.27641 | M70: =SUM(M32/M5) -> 118.06096 | N70: =SUM(N32/N5) -> 131.28101 | O70: =SUM(O32/O5) -> 112.67074 | P70: =SUM(P32/P5) -> 136.15061 | Q70: =SUM(Q32/Q5) -> 1633.8074 | R70: =SUM(R32/R5) -> 1633.8074
A71: LTV | C71: =SUM(C60/C9) -> -4217.3077 | D71: =SUM(D60/D9) -> -684.76342 | E71: =SUM(E60/E9) -> -114.35982 | F71: =SUM(F60/F9) -> -93.375202 | G71: =SUM(G60/G9) -> 409.01349 | H71: =SUM(H60/H9) -> 639.31614 | J71: =SUM(J60/J9) -> 635.0756 | K71: =SUM(K60/K9) -> 598.84983 | L71: =SUM(L60/L9) -> 480.96127 | M71: =SUM(M60/M9) -> 641.91233 | N71: =SUM(N60/N9) -> 661.41358 | O71: =SUM(O60/O9) -> 765.67445 | P71: =SUM(P60/P9) -> 1956.6594 | Q71: =SUM(Q60/Q9) -> 3435.7025 | R71: =SUM(R60/R9) -> 19418.792
A72: LTV : CAC | C72: =SUM(C71/C70) -> -13.890043 | D72: =SUM(D71/D70) -> -4.5106471 | E72: =SUM(E71/E70) -> -1.1299599 | F72: =SUM(F71/F70) -> -0.46375759 | G72: =SUM(G71/G70) -> 4.2039511 | H72: =SUM(H71/H70) -> 8.0677001 | J72: =SUM(J71/J70) -> 4.5926466 | K72: =SUM(K71/K70) -> 4.4722187 | L72: =SUM(L71/L70) -> 3.778872 | M72: =SUM(M71/M70) -> 5.4371259 | N72: =SUM(N71/N70) -> 5.038151 | O72: =SUM(O71/O70) -> 6.7956815 | P72: =SUM(P71/P70) -> 14.371286 | Q72: =SUM(Q71/Q70) -> 2.1028811 | R72: =SUM(R71/R70) -> 11.885607
A73: CAC Payback Days | C73: =SUM((C70/C60)*30) -> -7.1994017 | D73: =SUM((D70/D60)*30) -> -22.169768 | E73: =SUM((E70/E60)*30) -> -88.498716 | F73: =SUM((F70/F60)*30) -> -215.62989 | G73: =SUM((G70/G60)*30) -> 23.787146 | H73: =SUM((H70/H60)*30) -> 12.395106 | J73: =SUM((J70/J60)*30) -> 21.773938 | K73: =SUM((K70/K60)*30) -> 22.360266 | L73: =SUM((L70/L60)*30) -> 26.462923 | M73: =SUM((M70/M60)*30) -> 18.39207 | N73: =SUM((N70/N60)*30) -> 19.848552 | O73: =SUM((O70/O60)*30) -> 14.715228 | P73: =SUM((P70/P60)*30) -> 6.9583194 | Q73: =SUM((Q70/Q60)*30) -> 47.553807 | R73: =SUM((R70/R60)*30) -> 8.4135374
A74: Take Rate | C74: =SUM((C24/C65)*100) -> 11.15093 | D74: =SUM((D24/D65)*100) -> 10.372415 | E74: =SUM((E24/E65)*100) -> 12.578566 | F74: =SUM((F24/F65)*100) -> 12.271711 | G74: =SUM((G24/G65)*100) -> 10.976661 | H74: =SUM((H24/H65)*100) -> 10.418905 | J74: =SUM((J24/J65)*100) -> 11.383015 | K74: =SUM((K24/K65)*100) -> 11.007335 | L74: =SUM((L24/L65)*100) -> 11.413764 | M74: =SUM((M24/M65)*100) -> 11.943047 | N74: =SUM((N24/N65)*100) -> 11.914917 | O74: =SUM((O24/O65)*100) -> 12.211362 | P74: =SUM((P24/P65)*100) -> 38.326702 | Q74: =SUM((Q24/Q65)*100) -> 193.83602 | R74: =SUM((R24/R65)*100) -> 318.21197
A75: ARPU | C75: =SUM(C24/C12) -> 362.40523 | D75: =SUM(D24/D12) -> 337.10349 | E75: =SUM(E24/E12) -> 408.80341 | F75: =SUM(F24/F12) -> 398.8306 | G75: =SUM(G24/G12) -> 356.74148 | H75: =SUM(H24/H12) -> 338.61441 | J75: =SUM(J24/J12) -> 369.94798 | K75: =SUM(K24/K12) -> 357.73838 | L75: =SUM(L24/L12) -> 370.94733 | M75: =SUM(M24/M12) -> 388.14903 | N75: =SUM(N24/N12) -> 387.23481 | O75: =SUM(O24/O12) -> 396.86926 | P75: =SUM(P24/P12) -> 1245.6178 | Q75: =SUM(Q24/Q12) -> 6299.6706 | R75: =SUM(R24/R12) -> 10341.889
A76: Burn Rate | C76: =SUM(C24-C34) -> -722946.27 | D76: =SUM(D24-D34) -> -540213.81 | E76: =SUM(E24-E34) -> -424633.61 | F76: =SUM(F24-F34) -> -678883.69 | G76: =SUM(G24-G34) -> 112161.04 | H76: =SUM(H24-H34) -> 1247684.7 | J76: =SUM(J24-J34) -> 1323845.6 | K76: =SUM(K24-K34) -> 2266169.8 | L76: =SUM(L24-L34) -> 2360226.3 | M76: =SUM(M24-M34) -> 4558477.3 | N76: =SUM(N24-N34) -> 3528099.1 | O76: =SUM(O24-O34) -> -2770769.9 | P76: =SUM(P24-P34) -> 6037315.5 | Q76: =SUM(Q24-Q34) -> 1364250155 | R76: =SUM(R24-R34) -> 5515024183
A77: Burn Multiple
A78: Magic Number | D78: =SUM((D24-C24)*(12/C32)) -> 7.3092983 | E78: =SUM((E24-D24)*(12/D32)) -> 16.237235 | F78: =SUM((F24-E24)*(12/E32)) -> 17.295779 | G78: =SUM((G24-F24)*(12/F32)) -> 14.286118 | H78: =SUM((H24-G24)*(12/G32)) -> 14.018931 | J78: =SUM((J24-H24)*(12/H32)) -> 20.070093 | K78: =SUM((K24-J24)*(12/J32)) -> 12.402372 | L78: =SUM((L24-K24)*(12/K32)) -> 15.022925 | M78: =SUM((M24-L24)*(12/L32)) -> 16.056536 | N78: =SUM((N24-M24)*(12/M32)) -> 14.452153 | O78: =SUM((O24-N24)*(12/N32)) -> 15.790364 | P78: =SUM((P24-O24)*(12/O32)) -> 89.089497 | Q78: =SUM((Q24-P24)*(12/P32)) -> 466.77879 | R78: =SUM((R24-Q24)*(12/Q32)) -> 58.9357
A79: DAU / MAU
A80: Logo Churn
A81: Runway | C81: =SUM(C37/C34) -> 5.1843075 | D81: =SUM(D37/D34) -> 4.5295029 | E81: =SUM(E37/E34) -> 2.9696547 | F81: =SUM(F37/F34) -> 1.4613372 | G81: =SUM(G37/G34) -> 1.4019529 | H81: =SUM(H37/H34) -> 1.9823032 | J81: =SUM(J37/J34) -> 1.5640354 | K81: =SUM(K37/K34) -> 1.6903796 | L81: =SUM(L37/L34) -> 1.2646313 | M81: =SUM(M37/M34) -> 1.3168995 | N81: =SUM(N37/N34) -> 0.99395423 | O81: =SUM(O37/O34) -> 0.4536695
A82: NRR

Sheet Income Statement
A1: Financials
A2: Income statement projection
B3: ( values in ₹) | C3: AOV | D3: 650
C4: ACU | D4: 0.3
B5: Year 1 | C5: Year 2 | D5: Year 3
A6: Revenue
A7: Commission on Sales | B7: =SUM('Monthly BrakeDown'!P19) -> 42612278 | C7: ='Monthly BrakeDown'!Q19 -> 4.7119731e+08 | D7: ='Monthly BrakeDown'!R19 -> 1099460379
A8: Promoted Sales (5%) | B8: ='Monthly BrakeDown'!P20 -> 17024919 | C8: ='Monthly BrakeDown'!Q20 -> 1.8847892e+08 | D8: ='Monthly BrakeDown'!R20 -> 4.3978415e+08
A9: Business Subscription | B9: ='Monthly BrakeDown'!P21 -> 25289610 | C9: ='Monthly BrakeDown'!Q21 -> 6.9149306e+08 | D9: ='Monthly BrakeDown'!R21 -> 3892590961
A10: Affiliate | B10: =SUM('Monthly BrakeDown'!P22) -> 2619218.3 | C10: =SUM('Monthly BrakeDown'!Q22) -> 28996757 | D10: =SUM('Monthly BrakeDown'!R22) -> 67659100
A11: Subscription | B11: =SUM('Monthly BrakeDown'!P23) -> 12834170 | C11: =SUM('Monthly BrakeDown'!Q23) -> 1.4208411e+08 | D11: =SUM('Monthly BrakeDown'!R23) -> 3.3152959e+08
A12: Finance
A13: B2B Buying | C13: =SUM(Assumptions!C29*Assumptions!D29*Assumptions!F29) -> 11524884 | D13: =SUM(Assumptions!C29*Assumptions!D29*Assumptions!G29) -> 129753032
A15: Total Revenue | B15: =SUM(B7:B14) -> 1.0038019e+08 | C15: =SUM(C7:C14) -> 1533775039 | D15: =SUM(D7:D14) -> 5960777215
A16: Expenses
A17: Technology & Infrastructure Costs | B17: =SUM(Assumptions!C32) -> 6583333.3 | C17: =SUM(Assumptions!D32) -> 158000000 | D17: =SUM(Assumptions!E32) -> 316000000
A18: Marketing & User Acquisition: | B18: =SUM(Assumptions!C33) -> 36554873 | C18: =SUM(Assumptions!D33) -> 8.7731695e+08 | D18: =SUM(Assumptions!E33) -> 1754633901
A19: Business Development & Partnerships | B19: =SUM(Assumptions!C34) -> 16494693 | C19: =SUM(Assumptions!D34) -> 3.9587262e+08 | D19: =SUM(Assumptions!E34) -> 7.9174524e+08
A20: Customer Support Costs | B20: =SUM(Assumptions!C35) -> 4783333.3 | C20: =SUM(Assumptions!D35) -> 114800000 | D20: =SUM(Assumptions!E35) -> 229600000
A21: Team Building & Legal | B21: =SUM(Assumptions!C36) -> 4783333.3 | C21: =SUM(Assumptions!D36) -> 114800000 | D21: =SUM(Assumptions!E36) -> 229600000
A22: Rent and office Expenses | B22: =SUM(Assumptions!C37) -> 25093333 | C22: =SUM(Assumptions!D37) -> 602240000 | D22: =SUM(Assumptions!E37) -> 602240000
A24: Total User | B24: =SUM('Monthly BrakeDown'!P5) -> 268488.49 | C24: =SUM('Monthly BrakeDown'!Q5) -> 536976.99 | D24: =SUM('Monthly BrakeDown'!R5) -> 1073954
A25: Total Active User | B25: =SUM('Monthly BrakeDown'!P6) -> 80546.548 | C25: =SUM('Monthly BrakeDown'!Q6) -> 241639.64 | D25: =SUM('Monthly BrakeDown'!R6) -> 563825.84
A26: CAC | B26: =SUM(B18/B24) -> 136.15061 | C26: =SUM(C18/C24) -> 1633.8074 | D26: =SUM(D18/D24) -> 1633.8074
A27: CAC (Active User) | B27: =SUM(B18/B25) -> 453.83538 | C27: =SUM(C18/C25) -> 3630.683 | D27: =SUM(D18/D25) -> 3112.014
A28: Annual ARPU | B28: ₹5,814.32 | C28: ₹879.71 | D28: ₹785.90
A29: Payback Period | B29: =Assumptions!C51 | C29: =Assumptions!D51 | D29: =Assumptions!E51
B31: =Assumptions!C52 | C31: =Assumptions!D52 | D31: =Assumptions!E52
A32: Total expenses | B32: =SUM(B17:B22) -> 94292899 | C32: =SUM(C17:C22) -> 2263029573 | D32: =SUM(D17:D22) -> 3923819146
A34: Gross Earning before taxes | B34: =SUM(B15-B32) -> 6087295.7 | C34: =SUM(C15-C32) -> -7.2925453e+08 | D34: =SUM(D15-D32) -> 2036958070
A35: Taxes | B35: =Max(0,B34*Assumptions!C3) -> 1826188.7 | C35: =Max(0,C34*Assumptions!D3) -> 0 | D35: =D34*Assumptions!C3 -> 611087421
A36: Net Profit after tax | B36: =B34-B35 -> 4261107 | C36: =C34-C35 -> -7.2925453e+08 | D36: =D34-D35 -> 1425870649
A37: Profitability | B37: =B36/B15 -> 0.042449679 | C37: =C36/C15 -> -0.47546382 | D37: =D36/D15 -> 0.23920885
A39: EBITDA | B39: =B36+B35 -> 6087295.7 | C39: =C36+C35 -> -7.2925453e+08 | D39: =D36+D35 -> 2036958070
B40: =B39/B15 -> 0.060642398 | C40: =C39/C15 -> -0.47546382 | D40: =D39/D15 -> 0.34172693
A41: Valuation (INR) | B41: =SUM(B15*20) -> 2007603892 | C41: =SUM(C15*10) -> 15337750391 | D41: =SUM(D15*10) -> 59607772155
A42: USD | B42: =SUM(B41/85) -> 23618869 | C42: =SUM(C41/85) -> 1.8044412e+08 | D42: =SUM(D41/85) -> 7.0126791e+08
A44: Total Downloads | B44: =SUM('Monthly BrakeDown'!P11) -> 268488.49 | C44: =SUM('Monthly BrakeDown'!Q11) -> 805465.48 | D44: =SUM('Monthly BrakeDown'!R11) -> 1879419.5
A46: Fixed Cost
A47: Variable Cost
A48: Gross Margin (%)
A49: Net Profit Margin
A50: Contribution Margin
A51: CM per User
A52: Break Even Point
A53: CMGR
A54: ARR
A55: MRR / ARR
A56: GMV (Est.)
A57: Rule of 40
... A73: NRR

Sheet Assumptions
A1: Assumptions
A2: Income Statement ( values in INR )
A3: Taxes | C3: 0.3
B4: Phase 1 | D4: Phase 2
D5: Cash | F5: Funding
A6: Funding | B6: 0 | F6: 500000 | G6: Total | H6: =SUM(F6+D7) -> 3762093.2
A7: Cash | B7: 5000000 | D7: =SUM('Monthly BrakeDown'!H24) -> 3262093.2 | E7: Total | F7: =SUM(F6/3) -> 166666.67 | G7: Monthly | H7: =SUM(H6/3) -> 1254031.1
A8: Total investment | B8: =SUM(B7) -> 5000000 | D8: =SUM(D7) -> 3262093.2
A9: Monthky (6 month) | B9: =SUM(B8/6) -> 833333.33 | D9: =SUM(D8/3) -> 1087364.4 | E9: Monthly
A10: Rent and office Expenses | B10: =SUM(B9*C10) -> 66666.667 | C10: 0.08 | D10: =SUM('Monthly BrakeDown'!I27) -> 266666.67 | E10: 0.1 | F10: =SUM(F7*G10) -> 13333.333 | G10: 0.08 | H10: =SUM(D10+F10) -> 280000
A11: Team Building & Legal | B11: =SUM(B9*C11) -> 66666.667 | C11: 0.08 | D11: =SUM('Monthly BrakeDown'!I28) -> 300000 | E11: 0.12 | F11: =SUM(F7*G11) -> 13333.333 | G11: 0.08 | H11: =SUM(D11+F11) -> 313333.33
A12: Customer Support Costs | B12: =SUM(B9*C12) -> 66666.667 | C12: 0.08 | D12: =SUM('Monthly BrakeDown'!I29) -> 300000 | E12: 0.1 | F12: =SUM(F7*G12) -> 13333.333 | G12: 0.08 | H12: =SUM(D12+F12) -> 313333.33
A13: Technology & Infrastructure Costs | B13: =SUM(B9*C13) -> 166666.67 | C13: 0.2 | D13: =SUM('Monthly BrakeDown'!I30) -> 333333.33 | E13: =SUM(D13/D9) -> 0.30655164 | F13: =SUM(F7*G13) -> 33333.333 | G13: 0.2 | H13: =SUM(D13+F13) -> 366666.67
A14: Business Development & Partnerships | B14: =SUM(B9*C14) -> 158333.33 | C14: 0.19 | D14: =SUM('Monthly BrakeDown'!I31) -> 474316.83 | E14: 0.13 | F14: =SUM(F7*G14) -> 31666.667 | G14: 0.19 | H14: =SUM(D14+F14) -> 505983.5
A15: Marketing & User Acquisition: | B15: =SUM(B9*C15) -> 300000 | C15: 0.36 | D15: =SUM('Monthly BrakeDown'!I32) -> 1879917.5 | E15: =SUM(D15/D13) -> 5.6397525 | F15: =SUM(F7*G15) -> 60000 | G15: 0.36 | H15: =SUM(D15+F15) -> 1939917.5
A16: Buffer | B16: =SUM(B13*C16) -> 1666.6667 | C16: 0.01 | D16: =SUM('Monthly BrakeDown'!I33) -> 0 | E16: 0.05 | F16: =SUM(F7*G16) -> 1666.6667 | G16: 0.01 | H16: =SUM(D16+F16) -> 1666.6667
A19: User (per multiple of budget) | B19: =SUM('Customer Acquisition'!J33) -> 23295.167
A20: Order Value | B20: =SUM('Income Statement'!D3) -> 650
A21: Active User | B21: =SUM('Income Statement'!D4) -> 0.3
A22: Source of Revenu | B22: GMV | C22: Revenue | D22: # per month | E22: Total | F22: Total GMV per user
A23: Commission on Sales (5%) | B23: =SUM(B20) -> 650 | C23: =SUM(B23*0.05) -> 32.5 | D23: 5 | E23: =SUM(C23*D23) -> 162.5 | F23: =SUM(B23*D23) -> 3250
A24: Promoted Sales (5%) | B24: =SUM(B20) -> 650 | C24: =SUM(B24*0.05) -> 32.5 | D24: 2 | E24: =SUM(C24*D24) -> 65
A25: Business Subscription | C25: 1500 | D25: 1 | E25: =SUM(C25*D25) -> 1500
A26: Cash Store Afilates Commission | B26: 50 | C26: =SUM(B26*0.1) -> 5 | D26: 2 | E26: =SUM(C26*D26) -> 10
A27: User Subscription | C27: 49 | D27: 1 | E27: =SUM(C27*D27) -> 49
A28: Finance
A29: B2B Buying | C29: 500 | D29: 2 | E29: 10% of seller | F29: =SUM('Monthly BrakeDown'!Q18*0.1) -> 11524.884 | G29: =SUM('Monthly BrakeDown'!R18*0.2) -> 129753.03
A31: Expenses | C31: Year 1 | D31: Year 2 | E31: Year 3 | F31: Growth Rate
A32: Technology & Infrastructure Costs | C32: =SUM('Monthly BrakeDown'!P30) -> 6583333.3 | D32: =SUM('Monthly BrakeDown'!Q30) -> 158000000 | E32: =SUM('Monthly BrakeDown'!R30) -> 316000000
A33: Marketing & User Acquisition: | C33: =SUM('Monthly BrakeDown'!P32) -> 36554873 | D33: =SUM('Monthly BrakeDown'!Q32) -> 8.7731695e+08 | E33: =SUM('Monthly BrakeDown'!R32) -> 1754633901
A34: Business Development & Partnerships | C34: =SUM('Monthly BrakeDown'!P31) -> 16494693 | D34: =SUM('Monthly BrakeDown'!Q31) -> 3.9587262e+08 | E34: =SUM('Monthly BrakeDown'!R31) -> 7.9174524e+08
A35: Customer Support Costs | C35: =SUM('Monthly BrakeDown'!P29) -> 4783333.3 | D35: =SUM('Monthly BrakeDown'!Q29) -> 114800000 | E35: =SUM('Monthly BrakeDown'!R29) -> 229600000
A36: Team Building & Legal | C36: =SUM('Monthly BrakeDown'!P28) -> 4783333.3 | D36: =SUM('Monthly BrakeDown'!Q28) -> 114800000 | E36: =SUM('Monthly BrakeDown'!R28) -> 229600000
A37: Rent and office Expenses | C37: =SUM('Monthly BrakeDown'!P27) -> 25093333 | D37: =SUM('Monthly BrakeDown'!Q27) -> 602240000 | E37: =SUM('Monthly BrakeDown'!R27) -> 602240000
A39: Valuation (USD) | C39: =SUM('Income Statement'!B42) -> 23618869 | D39: =SUM('Income Statement'!C42) -> 1.8044412e+08 | E39: =SUM('Income Statement'!D42) -> 7.0126791e+08
A40: Total User

Sheet Customer Acquisition
F1: Budget | G1: no of | H1: Total Budget | I1: CAC | J1: New User
A3: Channel | B3: PAID ADS (META / GOOGLE) | C3: Meta app install ads | D3: 100000 | E3: 1 | F3: =SUM(D3*E3) -> 100000 | G3: 1 | H3: =SUM(F3*G3) -> 100000 | I3: 300 | J3: =SUM(H3/I3) -> 333.33333
C4: Google UAC | D4: 100000 | E4: 1 | F4: =SUM(D4*E4) -> 100000 | G4: 1 | H4: =SUM(F4*G4) -> 100000 | I4: 300 | J4: =SUM(H4/I4) -> 333.33333
B5: College Events & Campus Programs | C5: College Business Fest | D5: 200000 | E5: 1 | F5: =SUM(D5*E5) -> 200000 | G5: 1 | H5: =SUM(F5*G5) -> 200000 | I5: 66.666667 | J5: =SUM(H5/I5) -> 3000
C6: College Sports Fest | D6: 1000000 | E6: 1 | F6: =SUM(D6*E6) -> 1000000 | G6: 0.25 | H6: =SUM(F6*G6) -> 250000 | I6: 100 | J6: =SUM(H6/I6) -> 2500
C7: Campus ambassadors | D7: 3000 | E7: 1 | F7: =SUM(D7*E7) -> 3000 | G7: =SUM(G5) -> 1 | H7: =SUM(F7*G7) -> 3000 | I7: 30 | J7: =SUM(H7/I7) -> 100
C8: On-ground QR onboarding | D8: 1000 | E8: 1 | F8: =SUM(D8*E8) -> 1000 | G8: 1 | H8: =SUM(F8*G8) -> 1000 | I8: 10 | J8: =SUM(H8/I8) -> 100
E9: 1 | F9: =SUM(D9*E9) -> 0
B10: Merchant-led Acquisition | C10: “Pay with ReZ & Earn Cashback” boards | D10: 1500 | E10: 1 | F10: =SUM(D10*E10) -> 1500 | G10: =SUM('Monthly BrakeDown'!C18) -> 142.5 | H10: =SUM(F10*G10) -> 213750 | I10: 50 | J10: =SUM(H10/I10) -> 4275
C11: QR on bills / counters | D11: 300 | E11: 1 | F11: =SUM(D11*E11) -> 300 | G11: =SUM(G10) -> 142.5 | H11: =SUM(F11*G11) -> 42750 | I11: 50 | J11: =SUM(H11/I11) -> 855
C12: Merchant staff push (refferal) | D12: 1000 | E12: 1 | F12: =SUM(D12*E12) -> 1000 | G12: =SUM(G11) -> 142.5 | H12: =SUM(F12*G12) -> 142500 | I12: 100 | J12: =SUM(H12/I12) -> 1425
C13: Scan & earn coins | D13: 50 | E13: 1 | F13: =SUM(D13*E13) -> 50 | G13: =SUM(G12) -> 142.5 | H13: =SUM(F13*G13) -> 7125 | I13: 50 | J13: =SUM(H13/I13) -> 142.5
B15: Referral Programs | C15: User referral (coins) | D15: 100 | E15: 1 | F15: =SUM(D15*E15) -> 100 | G15: 1 | H15: =SUM(F15*G15) -> 100 | I15: 100 | J15: =SUM(H15/I15) -> 1
B17: Influencer & Creator Marketing | C17: Instagram reels | D17: 1000 | E17: 1 | F17: =SUM(D17*E17) -> 1000 | G17: =SUM(G5*100) -> 100 | H17: =SUM(F17*G17) -> 100000 | I17: 100 | J17: =SUM(H17/I17) -> 1000
C18: College creators | D18: 1000 | E18: 1 | F18: =SUM(D18*E18) -> 1000 | G18: =SUM(G5*100) -> 100 | H18: =SUM(F18*G18) -> 100000 | I18: 100 | J18: =SUM(H18/I18) -> 1000
C19: Hyperlocal food & lifestyle pages | D19: 5000 | E19: 1 | F19: =SUM(D19*E19) -> 5000 | G19: 10 | H19: =SUM(F19*G19) -> 50000 | I19: 100 | J19: =SUM(H19/I19) -> 500
B20: Flea Markets, Pop-ups & Community Events | C20: Flea markets | D20: 100000 | E20: 1 | F20: =SUM(D20*E20) -> 100000 | G20: 1 | H20: =SUM(F20*G20) -> 100000 | I20: 200 | J20: =SUM(H20/I20) -> 500 | K20: 100 for setup 100 for user downloads
C21: Malls / parks | D21: 100000 | E21: 1 | F21: =SUM(D21*E21) -> 100000 | G21: 1 | H21: =SUM(F21*G21) -> 100000 | I21: 100 | J21: =SUM(H21/I21) -> 1000
C22: Society events | D22: 100000 | E22: 1 | F22: =SUM(D22*E22) -> 100000 | G22: 1 | H22: =SUM(F22*G22) -> 100000 | I22: 100 | J22: =SUM(H22/I22) -> 1000
B23: Corporate Onboarding | C23: Company MoU | D23: 500 | E23: 1 | F23: =SUM(D23*E23) -> 500 | G23: 30 | H23: =SUM(F23*G23) -> 15000 | I23: 500 | J23: =SUM(H23/I23) -> 30
C24: HR partnerships | D24: 100 | E24: 1 | F24: =SUM(D24*E24) -> 100 | G24: =SUM(G23*20) -> 600 | H24: =SUM(F24*G24) -> 60000 | I24: 100 | J24: =SUM(H24/I24) -> 600
C25: Internal employee offers | D25: 100 | E25: 1 | F25: =SUM(D25*E25) -> 100 | G25: =SUM(G24) -> 600 | H25: =SUM(F25*G25) -> 60000 | I25: 100 | J25: =SUM(H25/I25) -> 600
B26: Zero-CAC / Near-Zero CAC Channels | C26: Social share | D26: 100 | E26: 1 | F26: =SUM(D26*E26) -> 100 | G26: 10 | H26: =SUM(F26*G26) -> 1000 | I26: 1 | J26: =SUM(H26/I26) -> 1000
C27: organic content | D27: 100 | E27: 1 | F27: =SUM(D27*E27) -> 100 | G27: 10 | H27: =SUM(F27*G27) -> 1000 | I27: 1 | J27: =SUM(H27/I27) -> 1000
C28: word of mouth | D28: 100 | E28: 1 | F28: =SUM(D28*E28) -> 100 | G28: 10 | H28: =SUM(F28*G28) -> 1000 | I28: 1 | J28: =SUM(H28/I28) -> 1000
E29: 1 | F29: =SUM(D29*E29) -> 0
B30: PARTNERSHIPS | C30: Co-brand | D30: 20 | E30: 1 | F30: =SUM(D30*E30) -> 20 | G30: 1000 | H30: =SUM(F30*G30) -> 20000 | I30: 20 | J30: =SUM(H30/I30) -> 1000
D33: =SUM(D3:D30) -> 1714970 | F33: =SUM(F3:F30) -> 1714970 | H33: =SUM(H3:H30) -> 1768225 | I33: =SUM(H33/J33) -> 75.905231 | J33: =SUM(J3:J30) -> 23295.167
A34: NEW Customer Acquire
B35: Budget required | C35: CAC | D35: Total user
A36: Ideal Conditioin | B36: =SUM(H33) -> 1768225 | C36: =SUM(I33) -> 75.905231 | D36: =SUM(B36/C36) -> 23295.167
A37: CAC | B37: 100 | C37: =SUM(I33) -> 75.905231 | D37: =SUM(B37/C37) -> 1.3174323
A38: Starting Budget | B38: =SUM(Assumptions!B15) -> 300000 | C38: =SUM(I33) -> 75.905231 | D38: =SUM(B38/C38) -> 3952.2968
B45: Business Devloepment | C45: PAID ADS (META / GOOGLE) | D45: Meta app install ads
D46: Google UAC
C47: Events | D47: Merchant events
D48: Local events
C49: Refferal | D49: Merchant refers
D50: User Referrs
C51: Digital Marketing
C53: SaS
C54: LOCAL ASSOCIATIONS & UNIONS
C55: B2B PARTNERSHIPS
B59: Total Budget | C59: CAM | D59: Total user
A60: Ideal condition | B60: 15000000 | C60: 1000 | D60: =SUM(B60/C60) -> 15000
A61: CAM | C61: =SUM(C60) -> 1000 | D61: =SUM(B61/C61) -> 0
A62: Starting Budget | B62: =SUM(Assumptions!B14) -> 158333.33 | C62: =SUM(C61) -> 1000 | D62: =SUM(B62/C62) -> 158.33333

Sheet Charts
E3: Revenue | F3: Net Profit
D5: Year 1 | E5: 0.782 | F5: 0.093
D6: Year 2 | E6: 2.4 | F6: 0.326
D7: Year 3 | E7: 24.9 | F7: 4.183
E24: Revenue | F24: Gross Profit | G24: Net Profit
D25: Year 1 | E25: =SUM('Income Statement'!B15) -> 1.0038019e+08 | F25: =SUM('Income Statement'!B34) -> 6087295.7 | G25: =SUM('Income Statement'!B36) -> 4261107
D26: Year 2 | E26: =SUM('Income Statement'!C15) -> 1533775039 | F26: =SUM('Income Statement'!C34) -> -7.2925453e+08 | G26: =SUM('Income Statement'!C36) -> -7.2925453e+08
D27: Year 3 | E27: =SUM('Income Statement'!D15) -> 5960777215 | F27: =SUM('Income Statement'!D34) -> 2036958070 | G27: =SUM('Income Statement'!D36) -> 1425870649
E30: =(E27-E25)/E25 -> 58.382005 | F30: =(F27-F25)/F25 -> 333.62446 | G30: =(G27-G25)/G25 -> 333.62446
